odoo/addons/l10n_es_facturae_face/README.rst
odoo/addons/l10n_es_facturae_face/__init__.py
odoo/addons/l10n_es_facturae_face/__manifest__.py
odoo/addons/l10n_es_facturae_face/data/face_data.xml
odoo/addons/l10n_es_facturae_face/i18n/ca.po
odoo/addons/l10n_es_facturae_face/i18n/es.po
odoo/addons/l10n_es_facturae_face/i18n/l10n_es_facturae_face.pot
odoo/addons/l10n_es_facturae_face/models/__init__.py
odoo/addons/l10n_es_facturae_face/models/account_invoice_integration.py
odoo/addons/l10n_es_facturae_face/models/account_invoice_integration_log.py
odoo/addons/l10n_es_facturae_face/models/account_invoice_integration_method.py
odoo/addons/l10n_es_facturae_face/models/config.py
odoo/addons/l10n_es_facturae_face/models/res_company.py
odoo/addons/l10n_es_facturae_face/models/res_partner.py
odoo/addons/l10n_es_facturae_face/models/wsse_signature.py
odoo/addons/l10n_es_facturae_face/static/description/icon.png
odoo/addons/l10n_es_facturae_face/tests/__init__.py
odoo/addons/l10n_es_facturae_face/tests/test_facturae_face.py
odoo/addons/l10n_es_facturae_face/views/res_company_view.xml
odoo/addons/l10n_es_facturae_face/views/res_config_views.xml
odoo/addons/l10n_es_facturae_face/wizard/__init__.py
odoo/addons/l10n_es_facturae_face/wizard/account_invoice_integration_cancel.py
odoo/addons/l10n_es_facturae_face/wizard/account_invoice_integration_cancel_view.xml
odoo11_addon_l10n_es_facturae_face-11.0.1.0.4.dist-info/METADATA
odoo11_addon_l10n_es_facturae_face-11.0.1.0.4.dist-info/WHEEL
odoo11_addon_l10n_es_facturae_face-11.0.1.0.4.dist-info/top_level.txt
odoo11_addon_l10n_es_facturae_face-11.0.1.0.4.dist-info/RECORD
